{
	"info": {
		"_postman_id": "ede1c31f-d552-4c0a-bd20-69b9aa2b8247",
		"name": "Project_03",
		"schema": "https://schema.getpostman.com/json/collection/v2.1.0/collection.json",
		"_exporter_id": "37261380"
	},
	"item": [
		{
			"name": "Client",
			"item": [
				{
					"name": "POST - Create Client",
					"request": {
						"method": "POST",
						"header": [],
						"body": {
							"mode": "raw",
							"raw": "{\r\n    \"name\":\"Eduardo\",\r\n    \"email\":\"decarli@gmail.com\"\r\n}",
							"options": {
								"raw": {
									"language": "json"
								}
							}
						},
						"url": {
							"raw": "http://localhost:8082/api/v1/client",
							"protocol": "http",
							"host": [
								"localhost"
							],
							"port": "8082",
							"path": [
								"api",
								"v1",
								"client"
							]
						}
					},
					"response": []
				},
				{
					"name": "GET - Find all Clients",
					"request": {
						"method": "GET",
						"header": [],
						"url": {
							"raw": "http://localhost:8082/api/v1/client",
							"protocol": "http",
							"host": [
								"localhost"
							],
							"port": "8082",
							"path": [
								"api",
								"v1",
								"client"
							]
						}
					},
					"response": []
				},
				{
					"name": "GET - Find Client By Id",
					"request": {
						"method": "GET",
						"header": [],
						"url": {
							"raw": "http://localhost:8082/api/v1/client/{{id}}",
							"protocol": "http",
							"host": [
								"localhost"
							],
							"port": "8082",
							"path": [
								"api",
								"v1",
								"client",
								"{{id}}"
							]
						}
					},
					"response": []
				},
				{
					"name": "GET - Find Client By Email",
					"request": {
						"method": "GET",
						"header": [],
						"url": {
							"raw": "http://localhost:8082/api/v1/client/email/{{email}}",
							"protocol": "http",
							"host": [
								"localhost"
							],
							"port": "8082",
							"path": [
								"api",
								"v1",
								"client",
								"email",
								"{{email}}"
							]
						}
					},
					"response": []
				},
				{
					"name": "PUT - Update Client By Id",
					"request": {
						"method": "PUT",
						"header": [],
						"body": {
							"mode": "raw",
							"raw": "{\r\n    \"name\":\"Rodrigo\",\r\n    \"email\":\"teste@gmail.com\"\r\n}",
							"options": {
								"raw": {
									"language": "json"
								}
							}
						},
						"url": {
							"raw": "http://localhost:8082/api/v1/client/{{id}}",
							"protocol": "http",
							"host": [
								"localhost"
							],
							"port": "8082",
							"path": [
								"api",
								"v1",
								"client",
								"{{id}}"
							]
						}
					},
					"response": []
				},
				{
					"name": "PUT - Update Client By Email",
					"request": {
						"method": "PUT",
						"header": [],
						"body": {
							"mode": "raw",
							"raw": "{\r\n    \"name\":\"Gustavo\",\r\n    \"email\":\"teste@gmail.com\"\r\n}",
							"options": {
								"raw": {
									"language": "json"
								}
							}
						},
						"url": {
							"raw": "http://localhost:8082/api/v1/client/email/{{email}}",
							"protocol": "http",
							"host": [
								"localhost"
							],
							"port": "8082",
							"path": [
								"api",
								"v1",
								"client",
								"email",
								"{{email}}"
							]
						}
					},
					"response": []
				},
				{
					"name": "DELETE - Delete Client By Id",
					"request": {
						"method": "DELETE",
						"header": [],
						"url": {
							"raw": "http://localhost:8082/api/v1/client/{{id}}",
							"protocol": "http",
							"host": [
								"localhost"
							],
							"port": "8082",
							"path": [
								"api",
								"v1",
								"client",
								"{{id}}"
							]
						}
					},
					"response": []
				}
			]
		},
		{
			"name": "Stock",
			"item": [
				{
					"name": "POST - Create Product",
					"request": {
						"method": "POST",
						"header": [],
						"body": {
							"mode": "raw",
							"raw": "{\r\n    \"name\":\"refri\",\r\n    \"quantity\": 4\r\n}",
							"options": {
								"raw": {
									"language": "json"
								}
							}
						},
						"url": {
							"raw": "http://localhost:8080/api/v1/stock",
							"protocol": "http",
							"host": [
								"localhost"
							],
							"port": "8080",
							"path": [
								"api",
								"v1",
								"stock"
							]
						}
					},
					"response": []
				},
				{
					"name": "PUT - Update Product",
					"request": {
						"method": "PUT",
						"header": [],
						"body": {
							"mode": "raw",
							"raw": "{\r\n    \"name\": \"agua\",\r\n    \"quantity\": 5\r\n}",
							"options": {
								"raw": {
									"language": "json"
								}
							}
						},
						"url": {
							"raw": "http://localhost:8080/api/v1/stock/{{id}}",
							"protocol": "http",
							"host": [
								"localhost"
							],
							"port": "8080",
							"path": [
								"api",
								"v1",
								"stock",
								"{{id}}"
							]
						}
					},
					"response": []
				},
				{
					"name": "GET - Find All Products",
					"request": {
						"method": "GET",
						"header": [],
						"url": {
							"raw": "http://localhost:8080/api/v1/stock",
							"protocol": "http",
							"host": [
								"localhost"
							],
							"port": "8080",
							"path": [
								"api",
								"v1",
								"stock"
							]
						}
					},
					"response": []
				},
				{
					"name": "GET - Find Product By Id",
					"request": {
						"method": "GET",
						"header": [],
						"url": {
							"raw": "http://localhost:8080/api/v1/stock/product/id/{{id}}",
							"protocol": "http",
							"host": [
								"localhost"
							],
							"port": "8080",
							"path": [
								"api",
								"v1",
								"stock",
								"product",
								"id",
								"{{id}}"
							]
						}
					},
					"response": []
				},
				{
					"name": "GET - Find Product By Name",
					"request": {
						"method": "GET",
						"header": [],
						"url": {
							"raw": "http://localhost:8080/api/v1/stock/product/name/refri",
							"protocol": "http",
							"host": [
								"localhost"
							],
							"port": "8080",
							"path": [
								"api",
								"v1",
								"stock",
								"product",
								"name",
								"refri"
							]
						}
					},
					"response": []
				},
				{
					"name": "GET - Remove Quantity",
					"request": {
						"method": "GET",
						"header": [],
						"url": {
							"raw": "http://localhost:8080/api/v1/stock/quantity/remove/{{quantidade}}/{{product_name}}",
							"protocol": "http",
							"host": [
								"localhost"
							],
							"port": "8080",
							"path": [
								"api",
								"v1",
								"stock",
								"quantity",
								"remove",
								"{{quantidade}}",
								"{{product_name}}"
							]
						}
					},
					"response": []
				},
				{
					"name": "GET - Add Quantity",
					"protocolProfileBehavior": {
						"disableBodyPruning": true
					},
					"request": {
						"method": "GET",
						"header": [],
						"body": {
							"mode": "raw",
							"raw": "",
							"options": {
								"raw": {
									"language": "json"
								}
							}
						},
						"url": {
							"raw": "http://localhost:8080/api/v1/stock/quantity/add/{{quantity}}/{{product_name}}",
							"protocol": "http",
							"host": [
								"localhost"
							],
							"port": "8080",
							"path": [
								"api",
								"v1",
								"stock",
								"quantity",
								"add",
								"{{quantity}}",
								"{{product_name}}"
							]
						}
					},
					"response": []
				},
				{
					"name": "DELETE - Delete a Product By Id",
					"request": {
						"method": "DELETE",
						"header": [],
						"url": {
							"raw": "http://localhost:8080/api/v1/stock/{{id}}",
							"protocol": "http",
							"host": [
								"localhost"
							],
							"port": "8080",
							"path": [
								"api",
								"v1",
								"stock",
								"{{id}}"
							]
						}
					},
					"response": []
				}
			]
		},
		{
			"name": "Order",
			"item": [
				{
					"name": "POST - Create Order",
					"request": {
						"method": "POST",
						"header": [],
						"body": {
							"mode": "raw",
							"raw": "{\r\n  \"clientEmail\": \"decarli@gmail.com\",\r\n  \"products\": [\r\n    {\r\n      \"name\": \"REFRI\",\r\n      \"quantity\": 1\r\n    }\r\n  ]\r\n}",
							"options": {
								"raw": {
									"language": "json"
								}
							}
						},
						"url": {
							"raw": "http://localhost:8081/api/v1/order",
							"protocol": "http",
							"host": [
								"localhost"
							],
							"port": "8081",
							"path": [
								"api",
								"v1",
								"order"
							]
						}
					},
					"response": []
				},
				{
					"name": "PUT - Update Order By Id",
					"request": {
						"method": "PUT",
						"header": [],
						"body": {
							"mode": "raw",
							"raw": "{\r\n  \"clientEmail\": \"decarli@gmail.com\",\r\n  \"products\": [\r\n    {\r\n      \"name\": \"agua\",\r\n      \"quantity\": 3\r\n    }\r\n  ]\r\n}",
							"options": {
								"raw": {
									"language": "json"
								}
							}
						},
						"url": {
							"raw": "http://localhost:8081/api/v1/order/update/{{id}}",
							"protocol": "http",
							"host": [
								"localhost"
							],
							"port": "8081",
							"path": [
								"api",
								"v1",
								"order",
								"update",
								"{{id}}"
							]
						}
					},
					"response": []
				},
				{
					"name": "GET - Find Orders By Email",
					"protocolProfileBehavior": {
						"disableBodyPruning": true
					},
					"request": {
						"method": "GET",
						"header": [],
						"body": {
							"mode": "raw",
							"raw": "",
							"options": {
								"raw": {
									"language": "json"
								}
							}
						},
						"url": {
							"raw": "http://localhost:8081/api/v1/order/historic/byEmail/{{email}}",
							"protocol": "http",
							"host": [
								"localhost"
							],
							"port": "8081",
							"path": [
								"api",
								"v1",
								"order",
								"historic",
								"byEmail",
								"{{email}}"
							]
						}
					},
					"response": []
				},
				{
					"name": "GET - Find Orders By Protocol",
					"protocolProfileBehavior": {
						"disableBodyPruning": true
					},
					"request": {
						"method": "GET",
						"header": [],
						"body": {
							"mode": "raw",
							"raw": "",
							"options": {
								"raw": {
									"language": "json"
								}
							}
						},
						"url": {
							"raw": "http://localhost:8081/api/v1/order/historic/byProtocol/{{protocol}}",
							"protocol": "http",
							"host": [
								"localhost"
							],
							"port": "8081",
							"path": [
								"api",
								"v1",
								"order",
								"historic",
								"byProtocol",
								"{{protocol}}"
							]
						}
					},
					"response": []
				},
				{
					"name": "GET - Find Order By Id",
					"protocolProfileBehavior": {
						"disableBodyPruning": true
					},
					"request": {
						"method": "GET",
						"header": [],
						"body": {
							"mode": "raw",
							"raw": "",
							"options": {
								"raw": {
									"language": "json"
								}
							}
						},
						"url": {
							"raw": "http://localhost:8081/api/v1/order/historic/byId/{{id}}",
							"protocol": "http",
							"host": [
								"localhost"
							],
							"port": "8081",
							"path": [
								"api",
								"v1",
								"order",
								"historic",
								"byId",
								"{{id}}"
							]
						}
					},
					"response": []
				},
				{
					"name": "GET - Find Product By Id",
					"protocolProfileBehavior": {
						"disableBodyPruning": true
					},
					"request": {
						"method": "GET",
						"header": [],
						"body": {
							"mode": "raw",
							"raw": "",
							"options": {
								"raw": {
									"language": "json"
								}
							}
						},
						"url": {
							"raw": "http://localhost:8081/api/v1/order/product/{{id}}",
							"protocol": "http",
							"host": [
								"localhost"
							],
							"port": "8081",
							"path": [
								"api",
								"v1",
								"order",
								"product",
								"{{id}}"
							]
						}
					},
					"response": []
				},
				{
					"name": "DELETE - Delete Order By Id",
					"request": {
						"method": "DELETE",
						"header": [],
						"url": {
							"raw": "http://localhost:8081/api/v1/order/{{id}}",
							"protocol": "http",
							"host": [
								"localhost"
							],
							"port": "8081",
							"path": [
								"api",
								"v1",
								"order",
								"{{id}}"
							]
						}
					},
					"response": []
				}
			]
		}
	]
}